_.py
under-0.0.1.dist-info/LICENSE
under-0.0.1.dist-info/METADATA
under-0.0.1.dist-info/WHEEL
under-0.0.1.dist-info/top_level.txt
under-0.0.1.dist-info/RECORD
