Metadata-Version: 2.1
Name: under
Version: 0.0.1
Summary: A collection of nice utility functions for Python, referenced by '_'.
Home-page: https://github.com/patrikkj/_
Author: Patrik Kjærran
Author-email: patrikkja@gmail.com
License: UNKNOWN
Platform: UNKNOWN
Classifier: Programming Language :: Python :: 3
Classifier: Programming Language :: Python :: 3.6
Classifier: Programming Language :: Python :: 3.7
Classifier: License :: OSI Approved :: MIT License
Classifier: Operating System :: Microsoft :: Windows
